balsamic/__main__.py
balsamic/balsamic.py
balsamic-0.2.94.dist-info/METADATA
balsamic-0.2.94.dist-info/WHEEL
balsamic-0.2.94.dist-info/top_level.txt
balsamic-0.2.94.dist-info/RECORD
