Metadata-Version: 2.1
Name: balsamic
Version: 0.2.94
Summary: Send malicious pickles via requests or sockets
Author: Witchdoctor (malectrica)
Keywords: python,hack,pickle,serialization,security,sockets,web
Classifier: Development Status :: 5 - Production/Stable
Classifier: Intended Audience :: Developers
Classifier: Programming Language :: Python :: 3
Classifier: Operating System :: Unix
Classifier: Operating System :: MacOS :: MacOS X
Classifier: Operating System :: Microsoft :: Windows
Requires-Dist: argparse
